_build/__init__.py
_build/clean.py
_build/dist.py
_build/test.py
_build/venv.py
py_build/__init__.py
py_build/__main__.py
py_build/build.py
py_build/funcs.py
py_build/main.py
tests/build_test/__init__.py
tests/build_test/_lib.py
tests/build_test/test.py
py_build-0.2.0.dist-info/LICENSE.txt
py_build-0.2.0.dist-info/METADATA
py_build-0.2.0.dist-info/WHEEL
py_build-0.2.0.dist-info/top_level.txt
py_build-0.2.0.dist-info/RECORD
