Metadata-Version: 2.1
Name: py-build
Version: 0.2.0
Summary: A package that can be used to create a build process
Home-page: https://github.com/Aesonus/py-build
Author: Cory Laughlin
Author-email: corylcomposinger@gmail.com
License: UNKNOWN
Platform: UNKNOWN
Classifier: Programming Language :: Python :: 3
Classifier: License :: OSI Approved :: MIT License
Classifier: Operating System :: OS Independent
